odsynth/__init__.py
odsynth/generator.py
odsynth/globals.py
odsynth/plugins_loader.py
odsynth/publisher.py
odsynth/schema.py
odsynth/utils.py
odsynth/core/__init__.py
odsynth/core/object_model.py
odsynth/entry_points/__init__.py
odsynth/entry_points/publish.py
odsynth/entry_points/synth.py
odsynth/formatters/__factory.py
odsynth/formatters/__init__.py
odsynth/formatters/abstract_formatter.py
odsynth/formatters/base_formatter.py
odsynth/formatters/delimited_text_formatter.py
odsynth/formatters/exceptions.py
odsynth/formatters/json_formatter.py
odsynth/formatters/pandas_formatter.py
odsynth/formatters/xml_formatter.py
odsynth/providers/__factory.py
odsynth/providers/__init__.py
odsynth/providers/random_int.py
odsynth/providers/simple_text.py
odsynth/providers/ssn.py
odsynth/writers/__factory.py
odsynth/writers/__init__.py
odsynth/writers/abstract_writer.py
odsynth/writers/disc_writer.py
odsynth/writers/exceptions.py
odsynth-0.0.4.dist-info/LICENSE
odsynth-0.0.4.dist-info/METADATA
odsynth-0.0.4.dist-info/WHEEL
odsynth-0.0.4.dist-info/entry_points.txt
odsynth-0.0.4.dist-info/top_level.txt
odsynth-0.0.4.dist-info/RECORD
