Metadata-Version: 2.1
Name: odsynth
Version: 0.0.4
Author-email: Kofi Baafi <kbaafi@gmail.com>
Maintainer-email: Kofi Baafi <kbaafi@gmail.com>
License: MIT License
Project-URL: Homepage, https://odsynth.readthedocs.io/
Project-URL: Documentation, https://odsynth.readthedocs.io/
Project-URL: Repository, https://github.com/duapa/odsynth.git
Keywords: data,data synthesis,faker,ETL,test data
Classifier: Development Status :: 2 - Pre-Alpha
Classifier: Programming Language :: Python
Requires-Python: >=3.10
License-File: LICENSE
Requires-Dist: faker ==26.0.0
Requires-Dist: typer ==0.12.3
Requires-Dist: pandas ==2.2.2
Requires-Dist: pyyaml ==6.0.1
